havista/__init__.py
havista_cli-0.1.0.dist-info/METADATA
havista_cli-0.1.0.dist-info/WHEEL
havista_cli-0.1.0.dist-info/entry_points.txt
havista_cli-0.1.0.dist-info/top_level.txt
havista_cli-0.1.0.dist-info/RECORD
