Metadata-Version: 2.4
Name: havista-cli
Version: 0.1.0
Summary: CLI minimale pour Havista, widget de home staging virtuel par IA (édité par Paitite).
Home-page: https://havista.fr
Author: Paitite
Author-email: contact@havista.fr
Project-URL: Site Havista, https://havista.fr
Project-URL: Widget IA immobilier, https://havista.fr/widget
Project-URL: Éditeur Paitite, https://paitite.com
Classifier: Programming Language :: Python :: 3
Classifier: License :: OSI Approved :: MIT License
Classifier: Operating System :: OS Independent
Classifier: Topic :: Scientific/Engineering :: Artificial Intelligence
Requires-Python: >=3.7
Dynamic: author
Dynamic: author-email
Dynamic: classifier
Dynamic: description
Dynamic: description-content-type
Dynamic: home-page
Dynamic: project-url
Dynamic: requires-python
Dynamic: summary
